refers/__init__.py
refers/cli.py
refers/compromise_black.py
refers/definitions.py
refers/errors.py
refers/refers.py
refers/tags.py
refers-0.0.4.dist-info/entry_points.txt
refers-0.0.4.dist-info/LICENSE
refers-0.0.4.dist-info/METADATA
refers-0.0.4.dist-info/WHEEL
refers-0.0.4.dist-info/RECORD
