Metadata-Version: 2.1
Name: refers
Version: 0.0.4
Summary: Reference code to improve explainability
License: MIT
Author: Daniel Stoops
Author-email: danielstoops25@gmail.com
Requires-Python: >=3.11,<4.0
Classifier: License :: OSI Approved :: MIT License
Classifier: Programming Language :: Python :: 3
Classifier: Programming Language :: Python :: 3.11
Classifier: Programming Language :: Python :: 3.12
Requires-Dist: black (>=24.2.0,<25.0.0)
Requires-Dist: toml (>=0.10.2,<0.11.0)
